environmentaltools/__init__.py
environmentaltools/common/__init__.py
environmentaltools/common/load.py
environmentaltools/common/read.py
environmentaltools/common/save.py
environmentaltools/common/utils.py
environmentaltools/common/write.py
environmentaltools/download/__init__.py
environmentaltools/download/cordex_data.py
environmentaltools/download/cordex_data_intake.py
environmentaltools/download/google_earth_engine.py
environmentaltools/download/google_image.py
environmentaltools/download/marine_copernicus.py
environmentaltools/download/open_street_images.py
environmentaltools/drone/__init__.py
environmentaltools/drone/build_scan_pattern.py
environmentaltools/drone/drone_missions.py
environmentaltools/graphics/__init__.py
environmentaltools/graphics/joint.py
environmentaltools/graphics/processes.py
environmentaltools/graphics/spatial.py
environmentaltools/graphics/spatiotemporal.py
environmentaltools/graphics/temporal.py
environmentaltools/graphics/utils.py
environmentaltools/processes/__init__.py
environmentaltools/processes/compute.py
environmentaltools/processes/load.py
environmentaltools/processes/waves.py
environmentaltools/processes/write.py
environmentaltools/spatial/__init__.py
environmentaltools/spatial/analysis.py
environmentaltools/spatial/geotools.py
environmentaltools/spatiotemporal/__init__.py
environmentaltools/spatiotemporal/bme.py
environmentaltools/spatiotemporal/covariance.py
environmentaltools/spatiotemporal/indicators.py
environmentaltools/spatiotemporal/multicriteria.py
environmentaltools/spatiotemporal/raster.py
environmentaltools/spatiotemporal/utils.py
environmentaltools/spectral/__init__.py
environmentaltools/spectral/analysis.py
environmentaltools/temporal/__init__.py
environmentaltools/temporal/analysis.py
environmentaltools/temporal/classification.py
environmentaltools/temporal/copula.py
environmentaltools/temporal/core.py
environmentaltools/temporal/regimes.py
environmentaltools/temporal/simulation.py
environmentaltools-2026.3.1.1.dist-info/METADATA
environmentaltools-2026.3.1.1.dist-info/WHEEL
environmentaltools-2026.3.1.1.dist-info/licenses/LICENSE
environmentaltools-2026.3.1.1.dist-info/RECORD
