Metadata-Version: 2.4
Name: environmentaltools
Version: 2026.3.1.1
Summary: environmentaltools is an open-source Python package for modular environmental management, integrating timeseries analysis, raster-based processing, decision matrices, sensor workflows, and legal-administrative support for coastal and terrestrial systems.
Project-URL: Homepage, https://barrier.dinamicambiental.es
Project-URL: Documentation, https://environmentaltools.readthedocs.io/
Project-URL: Tracker, https://github.com/mcobosb/environmentaltools/issues
Project-URL: Repository, https://github.com/mcobosb/environmentaltools
Project-URL: Changelog, https://github.com/mcobosb/environmentaltools/CHANGELOG.md
Author-email: Manuel Cobos <mcobosb@ugr.es>
Maintainer-email: Manuel Cobos <mcobosb@ugr.es>
License-Expression: GPL-3.0-or-later
License-File: LICENSE
Classifier: Development Status :: 4 - Beta
Classifier: Intended Audience :: Developers
Classifier: Programming Language :: Python :: 3.12
Classifier: Programming Language :: Python :: 3.13
Classifier: Topic :: Software Development :: Build Tools
Requires-Python: >=3.12
Requires-Dist: affine
Requires-Dist: cartopy
Requires-Dist: cdo
Requires-Dist: cdsapi
Requires-Dist: cmocean
Requires-Dist: configobj
Requires-Dist: earthengine-api
Requires-Dist: esgf-pyclient
Requires-Dist: folium
Requires-Dist: geedim
Requires-Dist: geemap
Requires-Dist: geopandas
Requires-Dist: glob2
Requires-Dist: intake-esgf
Requires-Dist: loguru
Requires-Dist: lxml
Requires-Dist: matplotlib
Requires-Dist: numpy
Requires-Dist: openpyxl
Requires-Dist: pandas
Requires-Dist: pillow
Requires-Dist: pydap
Requires-Dist: pymcdm
Requires-Dist: pypdf2
Requires-Dist: pyproj
Requires-Dist: pyshp
Requires-Dist: python-dotenv
Requires-Dist: pytmd
Requires-Dist: rasterio
Requires-Dist: requests
Requires-Dist: scikit-image
Requires-Dist: scikit-learn
Requires-Dist: scipy
Requires-Dist: seaborn
Requires-Dist: statsmodels
Requires-Dist: tabula-py
Requires-Dist: timescale
Requires-Dist: tqdm
Requires-Dist: utide
Requires-Dist: werkzeug
Requires-Dist: windrose
Requires-Dist: xarray
Provides-Extra: docs
Requires-Dist: sphinx; extra == 'docs'
Requires-Dist: sphinx-rtd-theme; extra == 'docs'
Provides-Extra: download
Requires-Dist: cdo; extra == 'download'
Requires-Dist: cdsapi; extra == 'download'
Requires-Dist: configobj; extra == 'download'
Requires-Dist: earthengine-api; extra == 'download'
Requires-Dist: esgf-pyclient; extra == 'download'
Requires-Dist: geedim; extra == 'download'
Requires-Dist: geemap; extra == 'download'
Requires-Dist: intake-esgf; extra == 'download'
Requires-Dist: pandas; extra == 'download'
Requires-Dist: pydap; extra == 'download'
Requires-Dist: requests; extra == 'download'
Requires-Dist: tqdm; extra == 'download'
Requires-Dist: werkzeug; extra == 'download'
Requires-Dist: xarray; extra == 'download'
Provides-Extra: processes
Requires-Dist: matplotlib; extra == 'processes'
Requires-Dist: numpy; extra == 'processes'
Requires-Dist: pandas; extra == 'processes'
Requires-Dist: scipy; extra == 'processes'
Requires-Dist: xarray; extra == 'processes'
Provides-Extra: spatial
Requires-Dist: folium; extra == 'spatial'
Requires-Dist: geopandas; extra == 'spatial'
Requires-Dist: matplotlib; extra == 'spatial'
Requires-Dist: numpy; extra == 'spatial'
Requires-Dist: pandas; extra == 'spatial'
Requires-Dist: pyproj; extra == 'spatial'
Requires-Dist: scipy; extra == 'spatial'
Provides-Extra: spatiotemporal
Requires-Dist: folium; extra == 'spatiotemporal'
Requires-Dist: geopandas; extra == 'spatiotemporal'
Requires-Dist: glob2; extra == 'spatiotemporal'
Requires-Dist: loguru; extra == 'spatiotemporal'
Requires-Dist: matplotlib; extra == 'spatiotemporal'
Requires-Dist: numpy; extra == 'spatiotemporal'
Requires-Dist: pandas; extra == 'spatiotemporal'
Requires-Dist: pymcdm; extra == 'spatiotemporal'
Requires-Dist: pyproj; extra == 'spatiotemporal'
Requires-Dist: scikit-image; extra == 'spatiotemporal'
Requires-Dist: scipy; extra == 'spatiotemporal'
Requires-Dist: xarray; extra == 'spatiotemporal'
Provides-Extra: spectral
Requires-Dist: matplotlib; extra == 'spectral'
Requires-Dist: numpy; extra == 'spectral'
Requires-Dist: pandas; extra == 'spectral'
Requires-Dist: pytmd; extra == 'spectral'
Requires-Dist: scipy; extra == 'spectral'
Requires-Dist: timescale; extra == 'spectral'
Requires-Dist: utide; extra == 'spectral'
Provides-Extra: temporal
Requires-Dist: loguru; extra == 'temporal'
Requires-Dist: matplotlib; extra == 'temporal'
Requires-Dist: numpy; extra == 'temporal'
Requires-Dist: pandas; extra == 'temporal'
Requires-Dist: scipy; extra == 'temporal'
